Metadata-Version: 2.1
Name: se-com-opts
Version: 1.0.4
Summary: 常用的selenium-webdriver设置
Home-page: https://gitee.com/joeyoung18/se_com_opts.git
Author: JoeYoung
Author-email: 1022104172@qq.com
License: MIT Licence
Keywords: selenium
Platform: windows
License-File: LICENSE
